setup.py
virtualenvwrapper/__init__.py
virtualenvwrapper/npm.py
virtualenvwrapper.npm.egg-info/PKG-INFO
virtualenvwrapper.npm.egg-info/SOURCES.txt
virtualenvwrapper.npm.egg-info/dependency_links.txt
virtualenvwrapper.npm.egg-info/entry_points.txt
virtualenvwrapper.npm.egg-info/namespace_packages.txt
virtualenvwrapper.npm.egg-info/requires.txt
virtualenvwrapper.npm.egg-info/top_level.txt