Metadata-Version: 1.0
Name: virtualenvwrapper.npm
Version: 0.1
Summary: Plugin for virtualenvwrapper to automatically encapsulate inside the virtual environmentany npm installed globaly when the venv is activated
Home-page: https://github.com/rach/virtualenvwrapper.npm
Author: Rach Belaid
Author-email: dev@ironbraces.com
License: UNKNOWN
Platform: UNKNOWN
